<?xml version="1.0" encoding="UTF-8"?>
<!DOCTYPE filesystem PUBLIC "-//NetBeans//DTD Filesystem 1.1//EN" "http://www.netbeans.org/dtds/filesystem-1_1.dtd">
<filesystem>
    <folder name="Actions">
        <folder name="File">
            <file name="kiyut-alkitab-actions-NewViewAction.instance">
                <attr name="instanceClass" stringvalue="kiyut.alkitab.actions.NewViewAction"/>
            </file>
        </folder>
        <folder name="Tools">
            <file name="kiyut-alkitab-actions-BookInstallerAction.instance">
                <attr name="instanceClass" stringvalue="kiyut.alkitab.actions.BookInstallerAction"/>
            </file>
        </folder>
        <folder name="Window">
            <file name="kiyut-alkitab-actions-BookshelfAction.instance">
                <attr name="instanceClass" stringvalue="kiyut.alkitab.actions.BookshelfAction"/>
            </file>
            <file name="kiyut-alkitab-actions-BookViewerAction.instance">
                <attr name="instanceClass" stringvalue="kiyut.alkitab.actions.BookViewerAction"/>
            </file>
            <file name="kiyut-alkitab-actions-BookNavigatorAction.instance">
                <attr name="instanceClass" stringvalue="kiyut.alkitab.actions.BookNavigatorAction"/>
            </file>
            <file name="kiyut-alkitab-actions-DailyDevotionsAction.instance">
                <attr name="instanceClass" stringvalue="kiyut.alkitab.actions.DailyDevotionsAction"/>
            </file>
            <file name="kiyut-alkitab-actions-DefinitionsAction.instance">
                <attr name="instanceClass" stringvalue="kiyut.alkitab.actions.DefinitionsAction"/>
            </file>
        </folder>
    </folder>
    <folder name="OptionsDialog">
        <file name="BookViewerOptionCategory.instance">
            <attr name="instanceClass" stringvalue="kiyut.alkitab.options.BookViewerOptionsCategory"/>
        </file>
    </folder>
    <folder name="Services">
        <folder name="Alkitab">
            <file name="CoreBookViewProvider.instance">
                <attr name="instanceClass" stringvalue="kiyut.alkitab.core.CoreBookViewProvider"/>
            </file>
        </folder>
    </folder>
    <folder name="Alkitab">
        <folder name="Bookshelf">
            <folder name="PopupMenu">
                <file name="kiyut-alkitab-actions-BookshelfOpenSelectedAction.instance">
                    <attr name="instanceClass" stringvalue="kiyut.alkitab.actions.BookshelfOpenSelectedAction"/>
                    <attr name="position" intvalue="10"/>
                </file>
                <file name="kiyut-alkitab-actions-BookshelfBookPropertiesAction.instance">
                    <attr name="instanceClass" stringvalue="kiyut.alkitab.actions.BookshelfBookPropertiesAction"/>
                    <attr name="position" intvalue="1000"/>
                </file>
            </folder>
        </folder>
    </folder>
</filesystem>
